setup.py
usa_spending/__init__.py
usa_spending/assistance.py
usa_spending/contracts.py
usa_spending/government_api.py
usa_spending/readable_keywords.py
usa_spending/subawards.py
usa_spending.egg-info/PKG-INFO
usa_spending.egg-info/SOURCES.txt
usa_spending.egg-info/dependency_links.txt
usa_spending.egg-info/top_level.txt
usa_spending/api/__init__.py
usa_spending/api/api.py
usa_spending/api/test_api.py
usa_spending/api/xml2dict/__init__.py
usa_spending/api/xml2dict/object_dict.py
usa_spending/api/xml2dict/test_xml2dict.py
usa_spending/api/xml2dict/xml2dict.py