Metadata-Version: 1.0
Name: usa-spending
Version: 1.1
Summary: Python API for the numerous APIs available through USA Spending.
Home-page: https://github.com/codeforamerica/usa_spending_python
Author: Zach Williams
Author-email: zach@codeforamerica.org
License: BSD
Keywords: usa_spending,USA Spending,usa api
Platform: UNKNOWN
Classifier: Development Status :: 5 - Production/Stable
Classifier: Intended Audience :: Developers
Classifier: Natural Language :: English
Classifier: Operating System :: OS Independent
Classifier: Programming Language :: Python :: 2
Classifier: Topic :: Internet
Classifier: Topic :: Internet :: WWW/HTTP
